gpt_repository_loader/__init__.py
gpt_repository_loader/gpt_repository_loader.py
gpt_repository_loader/version.py
gpt_repository_loader-0.9.20.dist-info/LICENSE
gpt_repository_loader-0.9.20.dist-info/METADATA
gpt_repository_loader-0.9.20.dist-info/WHEEL
gpt_repository_loader-0.9.20.dist-info/entry_points.txt
gpt_repository_loader-0.9.20.dist-info/top_level.txt
gpt_repository_loader-0.9.20.dist-info/RECORD
