Metadata-Version: 2.1
Name: gpt-repository-loader
Version: 0.9.20
Summary: A utility to convert a Git repository into a text representation.
Home-page: https://github.com/felvin-search/gpt-repository-loader
Author: Felvin
Author-email: team@felvin.com
Classifier: Development Status :: 3 - Alpha
Classifier: Intended Audience :: Developers
Classifier: License :: OSI Approved :: MIT License
Classifier: Operating System :: OS Independent
Classifier: Programming Language :: Python :: 3
Classifier: Programming Language :: Python :: 3.6
Classifier: Programming Language :: Python :: 3.7
Classifier: Programming Language :: Python :: 3.8
Classifier: Programming Language :: Python :: 3.9
Requires-Python: >=3.6
License-File: LICENSE
Requires-Dist: pyperclip
Requires-Dist: token_count
Requires-Dist: tabulate
